aiopvapi/__init__.py
aiopvapi/__version__.py
aiopvapi/automations.py
aiopvapi/hub.py
aiopvapi/rooms.py
aiopvapi/scene_members.py
aiopvapi/scenes.py
aiopvapi/shades.py
aiopvapi/example/__init__.py
aiopvapi/example/hub.py
aiopvapi/example/rooms.py
aiopvapi/example/scene_members.py
aiopvapi/example/shade.py
aiopvapi/helpers/__init__.py
aiopvapi/helpers/aiorequest.py
aiopvapi/helpers/api_base.py
aiopvapi/helpers/constants.py
aiopvapi/helpers/powerview_util.py
aiopvapi/helpers/shade_types.py
aiopvapi/helpers/tools.py
aiopvapi/resources/__init__.py
aiopvapi/resources/automation.py
aiopvapi/resources/model.py
aiopvapi/resources/room.py
aiopvapi/resources/scene.py
aiopvapi/resources/scene_member.py
aiopvapi/resources/shade.py
aiopvapi/resources/shade_data.py
aiopvapi-3.3.0.dist-info/licenses/LICENSE
aiopvapi-3.3.0.dist-info/METADATA
aiopvapi-3.3.0.dist-info/WHEEL
aiopvapi-3.3.0.dist-info/entry_points.txt
aiopvapi-3.3.0.dist-info/top_level.txt
aiopvapi-3.3.0.dist-info/RECORD
